ai69/__init__.py
ai69/core.py
ai69-0.1.1.dist-info/LICENSE
ai69-0.1.1.dist-info/METADATA
ai69-0.1.1.dist-info/WHEEL
ai69-0.1.1.dist-info/top_level.txt
ai69-0.1.1.dist-info/RECORD
