Metadata-Version: 2.1
Name: ai69
Version: 0.1.1
Summary: An AI function generator for runtime
Home-page: https://github.com/sr2echa/ai69
Author: Sreecharan S.
Classifier: Programming Language :: Python :: 3
Classifier: License :: OSI Approved :: MIT License
Classifier: Operating System :: OS Independent
Requires-Python: >=3.6
License-File: LICENSE
Requires-Dist: requests
